setup.py
fakemp.egg-info/PKG-INFO
fakemp.egg-info/SOURCES.txt
fakemp.egg-info/dependency_links.txt
fakemp.egg-info/top_level.txt
lib/fakemp/__init__.py