Metadata-Version: 1.0
Name: fakemp
Version: 0.9.1
Summary: Fake multiprocessing pool objects
Home-page: UNKNOWN
Author: N Lance Hepler
Author-email: nlhepler@gmail.com
License: GNU GPL version 3
Platform: UNKNOWN
